odoo/addons/business_requirement_sale/README.rst
odoo/addons/business_requirement_sale/__init__.py
odoo/addons/business_requirement_sale/__manifest__.py
odoo/addons/business_requirement_sale/i18n/business_requirement_sale.pot
odoo/addons/business_requirement_sale/i18n/es.po
odoo/addons/business_requirement_sale/i18n/fr.po
odoo/addons/business_requirement_sale/i18n/pt_BR.po
odoo/addons/business_requirement_sale/i18n/sl.po
odoo/addons/business_requirement_sale/migrations/12.0.1.0.0/post-migration.py
odoo/addons/business_requirement_sale/models/__init__.py
odoo/addons/business_requirement_sale/models/business_requirement.py
odoo/addons/business_requirement_sale/models/sale_order.py
odoo/addons/business_requirement_sale/models/sale_order_line.py
odoo/addons/business_requirement_sale/readme/CONTRIBUTORS.rst
odoo/addons/business_requirement_sale/readme/DESCRIPTION.rst
odoo/addons/business_requirement_sale/readme/ROADMAP.rst
odoo/addons/business_requirement_sale/readme/USAGE.rst
odoo/addons/business_requirement_sale/static/description/icon.png
odoo/addons/business_requirement_sale/static/description/index.html
odoo/addons/business_requirement_sale/tests/__init__.py
odoo/addons/business_requirement_sale/tests/test_business_requirement_sale.py
odoo/addons/business_requirement_sale/views/business_requirement_views.xml
odoo/addons/business_requirement_sale/views/sale_order_views.xml
odoo/addons/business_requirement_sale/wizard/__init__.py
odoo/addons/business_requirement_sale/wizard/business_requirement_create_sale.py
odoo/addons/business_requirement_sale/wizard/business_requirement_create_sale_views.xml
odoo12_addon_business_requirement_sale-12.0.1.0.0.99.dev14.dist-info/METADATA
odoo12_addon_business_requirement_sale-12.0.1.0.0.99.dev14.dist-info/WHEEL
odoo12_addon_business_requirement_sale-12.0.1.0.0.99.dev14.dist-info/top_level.txt
odoo12_addon_business_requirement_sale-12.0.1.0.0.99.dev14.dist-info/RECORD
